omeka_s_tools2/__init__.py
omeka_s_tools2/_modidx.py
omeka_s_tools2/api.py
omeka_s_tools2/core.py
omeka_s_tools2-0.0.5.dist-info/LICENSE
omeka_s_tools2-0.0.5.dist-info/METADATA
omeka_s_tools2-0.0.5.dist-info/WHEEL
omeka_s_tools2-0.0.5.dist-info/entry_points.txt
omeka_s_tools2-0.0.5.dist-info/top_level.txt
omeka_s_tools2-0.0.5.dist-info/RECORD
