Metadata-Version: 2.1
Name: omeka-s-tools2
Version: 0.0.5
Home-page: https://github.com/nakamura196/omeka_s_tools2
Author: Satoru
Author-email: na.kamura.1263@gmail.com
License: Apache Software License 2.0
Keywords: nbdev jupyter notebook python
Classifier: Development Status :: 4 - Beta
Classifier: Intended Audience :: Developers
Classifier: Natural Language :: English
Classifier: Programming Language :: Python :: 3.7
Classifier: Programming Language :: Python :: 3.8
Classifier: Programming Language :: Python :: 3.9
Classifier: Programming Language :: Python :: 3.10
Classifier: License :: OSI Approved :: Apache Software License
Requires-Python: >=3.7
License-File: LICENSE
Requires-Dist: requests
Requires-Dist: requests-cache
Requires-Dist: pytest
Requires-Dist: python-dotenv
Provides-Extra: dev
